ezbotf/__init__.py
ezbotf/cli.py
ezbotf/common.py
ezbotf/context.py
ezbotf/exceptions.py
ezbotf/ezlog.py
ezbotf/instance.py
ezbotf/instancecontext.py
ezbotf/messages.py
ezbotf/permissions.py
ezbotf/plugin.py
ezbotf/pluginloader.py
ezbotf/translator.py
ezbotf/types.py
ezbotf/utils.py
ezbotf/version.py
ezbotf/argumentparser/__init__.py
ezbotf/argumentparser/_casts.py
ezbotf/argumentparser/argumentparseerror.py
ezbotf/argumentparser/casts.py
ezbotf/argumentparser/parser.py
ezbotf-1.0.0.dist-info/LICENSE
ezbotf-1.0.0.dist-info/METADATA
ezbotf-1.0.0.dist-info/WHEEL
ezbotf-1.0.0.dist-info/entry_points.txt
ezbotf-1.0.0.dist-info/top_level.txt
ezbotf-1.0.0.dist-info/RECORD
