Metadata-Version: 2.1
Name: ezbotf
Version: 1.0.0
Summary: Create own plugins for Telegram through this framework
Author-email: ftdot <ftdoot@gmail.com>
License: MIT License
Project-URL: Homepage, https://github.com/ftdot/ezbotf
Keywords: telegram,framework,plugins,easy
Classifier: Environment :: Plugins
Classifier: Framework :: Sphinx
Classifier: Natural Language :: English
Classifier: License :: OSI Approved :: MIT License
Classifier: Programming Language :: Python
Classifier: Programming Language :: Python :: 3
Classifier: Programming Language :: Python :: 3.10
Classifier: Topic :: Communications :: Chat
Classifier: Topic :: Documentation :: Sphinx
Requires-Python: >=3.10
License-File: LICENSE
Requires-Dist: telethon
Requires-Dist: colorama (~=0.4.6)
Requires-Dist: tomlkit (~=0.11.6)
Requires-Dist: nest-asyncio
Requires-Dist: verlib
Provides-Extra: docs
Requires-Dist: sphinx ; extra == 'docs'
Requires-Dist: sphinx-rtd-theme ; extra == 'docs'
